MANIFEST.in
README.md
setup.py
datetimerangepicker/DateTimeRangePicker.py
datetimerangepicker/__init__.py
datetimerangepicker/_imports_.py
datetimerangepicker/datetimerangepicker.dev.js
datetimerangepicker/datetimerangepicker.min.js
datetimerangepicker/metadata.json
datetimerangepicker/package.json
datetimerangepicker.egg-info/PKG-INFO
datetimerangepicker.egg-info/SOURCES.txt
datetimerangepicker.egg-info/dependency_links.txt
datetimerangepicker.egg-info/top_level.txt