Metadata-Version: 1.0
Name: datetimerangepicker
Version: 0.0.1
Summary: Project Description
Home-page: UNKNOWN
Author: kraglik igor igor.kraglik@yandex.ru
Author-email: UNKNOWN
License: MIT
Platform: UNKNOWN
